lacerta/__init__.py
lacerta/base.py
lacerta/correlations.py
lacerta-0.1.2.dist-info/LICENSE
lacerta-0.1.2.dist-info/METADATA
lacerta-0.1.2.dist-info/WHEEL
lacerta-0.1.2.dist-info/top_level.txt
lacerta-0.1.2.dist-info/RECORD
