Metadata-Version: 2.2
Name: lacerta
Version: 0.1.2
Summary: Interactive data viz for science and engineering
Home-page: https://github.com/imperssonator/lacerta
Author: Nils Persson
Author-email: imperssonator@gmail.com
Project-URL: Bug Tracker, https://github.com/imperssonator/lacerta/issues
Classifier: Programming Language :: Python :: 3
Classifier: License :: OSI Approved :: Apache Software License
Classifier: Operating System :: OS Independent
Requires-Python: >=3.9
License-File: LICENSE
Requires-Dist: bokeh>=3.0.3
Requires-Dist: pandas>=1.5.3
Requires-Dist: numpy>=1.24.2
Requires-Dist: scipy>=1.15
